heckorator/Cozette-13.bdf
heckorator/__init__.py
heckorator/__main__.py
heckorator/default_font.py
heckorator-0.1.5.dist-info/LICENSE
heckorator-0.1.5.dist-info/METADATA
heckorator-0.1.5.dist-info/WHEEL
heckorator-0.1.5.dist-info/RECORD
