Metadata-Version: 2.1
Name: heckorator
Version: 0.1.5
Summary: the most readable decorators you've ever seen
Home-page: https://github.com/RocketRace/heckorator
License: MIT
Author: RocketRace
Author-email: hiemankaranteenissa@proton.me
Requires-Python: >=3.12
Classifier: License :: OSI Approved :: MIT License
Classifier: Programming Language :: Python :: 3
Classifier: Programming Language :: Python :: 3.12
Requires-Dist: bdfparser (>=2.2.0,<3.0.0)
Project-URL: Repository, https://github.com/RocketRace/heckorator
